README.md
setup.py
jschema/__init__.py
jschema/context.py
jschema/errors.py
jschema/load_schemas.py
jschema/main.py
jschema/version.py
jschema.egg-info/PKG-INFO
jschema.egg-info/SOURCES.txt
jschema.egg-info/dependency_links.txt
jschema.egg-info/entry_points.txt
jschema.egg-info/requires.txt
jschema.egg-info/top_level.txt
jschema/docs/__init__.py
jschema/docs/make_docs.py
jschema/docs/templates/index.j2
jschema/docs/templates/layout.j2
jschema/docs/templates/schema.j2
jschema/docs/vendor/highlight-monokai-sublime.css
jschema/docs/vendor/highlight.pack.js
jschema/refs_resolver/__init__.py
jschema/refs_resolver/refs_group.py
jschema/refs_resolver/refs_resolver.py
jschema/schema/__init__.py
jschema/schema/node.py
jschema/schema/refs_resolver.py
jschema/schema/schema.py