Metadata-Version: 1.2
Name: jschema
Version: 7.1.2
Summary: Json Schema compiler
Home-page: https://github.com/stepan-perlov/jschema
Author: Stepan Perlov
Author-email: stepanperlov@gmail.com
License: MIT
Platform: linux
Classifier: Development Status :: 5 - Production/Stable
Classifier: Intended Audience :: Developers
Classifier: Topic :: Software Development :: Build Tools
Classifier: License :: OSI Approved :: MIT License
Classifier: Programming Language :: Python :: 3
Requires-Python: >=3
